binance_sdk_vip_loan/__init__.py
binance_sdk_vip_loan/metadata.py
binance_sdk_vip_loan/rest_api/__init__.py
binance_sdk_vip_loan/rest_api/api/__init__.py
binance_sdk_vip_loan/rest_api/api/market_data_api.py
binance_sdk_vip_loan/rest_api/api/trade_api.py
binance_sdk_vip_loan/rest_api/api/user_information_api.py
binance_sdk_vip_loan/rest_api/models/__init__.py
binance_sdk_vip_loan/rest_api/models/check_vip_loan_collateral_account_response.py
binance_sdk_vip_loan/rest_api/models/check_vip_loan_collateral_account_response_rows_inner.py
binance_sdk_vip_loan/rest_api/models/enums.py
binance_sdk_vip_loan/rest_api/models/get_borrow_interest_rate_response.py
binance_sdk_vip_loan/rest_api/models/get_borrow_interest_rate_response_inner.py
binance_sdk_vip_loan/rest_api/models/get_collateral_asset_data_response.py
binance_sdk_vip_loan/rest_api/models/get_collateral_asset_data_response_rows_inner.py
binance_sdk_vip_loan/rest_api/models/get_loanable_assets_data_response.py
binance_sdk_vip_loan/rest_api/models/get_loanable_assets_data_response_rows_inner.py
binance_sdk_vip_loan/rest_api/models/get_vip_loan_accrued_interest_response.py
binance_sdk_vip_loan/rest_api/models/get_vip_loan_accrued_interest_response_rows_inner.py
binance_sdk_vip_loan/rest_api/models/get_vip_loan_interest_rate_history_response.py
binance_sdk_vip_loan/rest_api/models/get_vip_loan_interest_rate_history_response_rows_inner.py
binance_sdk_vip_loan/rest_api/models/get_vip_loan_ongoing_orders_response.py
binance_sdk_vip_loan/rest_api/models/get_vip_loan_ongoing_orders_response_rows_inner.py
binance_sdk_vip_loan/rest_api/models/query_application_status_response.py
binance_sdk_vip_loan/rest_api/models/query_application_status_response_rows_inner.py
binance_sdk_vip_loan/rest_api/models/vip_loan_borrow_response.py
binance_sdk_vip_loan/rest_api/models/vip_loan_renew_response.py
binance_sdk_vip_loan/rest_api/models/vip_loan_repay_response.py
binance_sdk_vip_loan/rest_api/rest_api.py
binance_sdk_vip_loan/vip_loan.py
binance_sdk_vip_loan-5.0.0.dist-info/METADATA
binance_sdk_vip_loan-5.0.0.dist-info/WHEEL
binance_sdk_vip_loan-5.0.0.dist-info/licenses/LICENCE
binance_sdk_vip_loan-5.0.0.dist-info/RECORD
